sgd/__init__.py
sgd/api.py
sgd/constants.py
sgd/exceptions.py
sgd/data/genes_to_loci.json
sgd_rest-0.2.1.dist-info/licenses/LICENSE
sgd_rest-0.2.1.dist-info/METADATA
sgd_rest-0.2.1.dist-info/WHEEL
sgd_rest-0.2.1.dist-info/top_level.txt
sgd_rest-0.2.1.dist-info/RECORD
