Metadata-Version: 2.4
Name: sgd-rest
Version: 0.2.1
Summary: Saccharomyces Genome Database (SGD) REST API wrapper
Author-email: Ira Horecka <ira89@icloud.com>
License: MIT
Project-URL: Homepage, https://github.com/irahorecka/sgd-rest
Classifier: Intended Audience :: Developers
Classifier: Operating System :: OS Independent
Classifier: Programming Language :: Python :: 3.8
Classifier: Programming Language :: Python :: 3.9
Classifier: Programming Language :: Python :: 3.10
Classifier: Programming Language :: Python :: 3.11
Classifier: Programming Language :: Python :: 3.12
Classifier: Topic :: Software Development :: Libraries
Classifier: Topic :: Utilities
Requires-Python: >=3.8
License-File: LICENSE
Requires-Dist: requests>=2.28.0
Dynamic: license-file
